README.txt
ReverseFolderContents.ReverseFolderContents-configure.zcml
setup.py
ReverseFolderContents/__init__.py
ReverseFolderContents.ReverseFolderContents.egg-info/PKG-INFO
ReverseFolderContents.ReverseFolderContents.egg-info/SOURCES.txt
ReverseFolderContents.ReverseFolderContents.egg-info/dependency_links.txt
ReverseFolderContents.ReverseFolderContents.egg-info/entry_points.txt
ReverseFolderContents.ReverseFolderContents.egg-info/namespace_packages.txt
ReverseFolderContents.ReverseFolderContents.egg-info/not-zip-safe
ReverseFolderContents.ReverseFolderContents.egg-info/requires.txt
ReverseFolderContents.ReverseFolderContents.egg-info/top_level.txt
ReverseFolderContents/ReverseFolderContents/__init__.py
ReverseFolderContents/ReverseFolderContents/changes.txt
ReverseFolderContents/ReverseFolderContents/configure.zcml
ReverseFolderContents/ReverseFolderContents/messages.py
ReverseFolderContents/ReverseFolderContents/readme.txt
ReverseFolderContents/ReverseFolderContents/i18n/plone-no.po
ReverseFolderContents/ReverseFolderContents/profiles/default/metadata.xml
ReverseFolderContents/ReverseFolderContents/profiles/default/skins.xml
ReverseFolderContents/ReverseFolderContents/skins/ReverseFolderContents/getFolderContents.py
docs/HISTORY.txt