Metadata-Version: 1.0
Name: ReverseFolderContents.ReverseFolderContents
Version: 1.0.3
Summary: Enables reversing the listing of the folder contents in different views as well as in the navigation
Home-page: http://www.nidelven-it.no/d/
Author: Morten W. Petersen
Author-email: info@nidelven-it.no
License: GPL 2
Keywords: python zope plone layout navigation monkeypatch archetypes
Platform: UNKNOWN
Classifier: Programming Language :: Python
Classifier: Framework :: Plone
Classifier: Framework :: Zope2
Classifier: Intended Audience :: End Users/Desktop
Classifier: License :: OSI Approved :: GNU General Public License (GPL)
Classifier: Operating System :: OS Independent
